<annotation>
  <folder>train_1</folder>
  <filename>image_LasMeninas_203.jpg</filename>
  <path>C:\Users\Alexander\Desktop\train_1\image_LasMeninas_203.jpg</path>
  <source>
    <database>Unknown</database>
  </source>
  <size>
    <width>1668</width>
    <height>1920</height>
    <depth>3</depth>
  </size>
  <segmented>0</segmented>
  <object>
    <name>Diego Velazquez</name>
    <pose>Unspecified</pose>
    <truncated>0</truncated>
    <difficult>0</difficult>
    <bndbox>
      <xmin>249</xmin>
      <ymin>919</ymin>
      <xmax>522</xmax>
      <ymax>1226</ymax>
    </bndbox>
  </object>
  <object>
    <name>Maria Agustina</name>
    <pose>Unspecified</pose>
    <truncated>0</truncated>
    <difficult>0</difficult>
    <bndbox>
      <xmin>356</xmin>
      <ymin>1206</ymin>
      <xmax>659</xmax>
      <ymax>1507</ymax>
    </bndbox>
  </object>
  <object>
    <name>Infanta Margarita</name>
    <pose>Unspecified</pose>
    <truncated>0</truncated>
    <difficult>0</difficult>
    <bndbox>
      <xmin>659</xmin>
      <ymin>1192</ymin>
      <xmax>950</xmax>
      <ymax>1600</ymax>
    </bndbox>
  </object>
  <object>
    <name>Isabel de Velasco</name>
    <pose>Unspecified</pose>
    <truncated>0</truncated>
    <difficult>0</difficult>
    <bndbox>
      <xmin>944</xmin>
      <ymin>1056</ymin>
      <xmax>1283</xmax>
      <ymax>1416</ymax>
    </bndbox>
  </object>
  <object>
    <name>Mari Barbola</name>
    <pose>Unspecified</pose>
    <truncated>0</truncated>
    <difficult>0</difficult>
    <bndbox>
      <xmin>1288</xmin>
      <ymin>1155</ymin>
      <xmax>1534</xmax>
      <ymax>1503</ymax>
    </bndbox>
  </object>
</annotation>
